{
    "measurements": [
        {
            "name": "Area",
            "value": "area"
        },
        {
            "name": "Currency",
            "value": "currency"
        },
        {
            "name": "Length",
            "value": "length"
        },
        {
            "name": "Temperature",
            "value": "temperature"
        },
        {
            "name": "Volume",
            "value": "volume"
        },
        {
            "name": "Weight",
            "value": "weight"
        }
    ]
}